wechatrobot/Api.py
wechatrobot/Bus.py
wechatrobot/ChatRoomData_pb2.py
wechatrobot/Modles.py
wechatrobot/Utils.py
wechatrobot/WeChatRobot.py
wechatrobot/__init__.py
wechatrobot/__version__.py
python_comwechatrobot_http-1.0.1.dist-info/METADATA
python_comwechatrobot_http-1.0.1.dist-info/WHEEL
python_comwechatrobot_http-1.0.1.dist-info/top_level.txt
python_comwechatrobot_http-1.0.1.dist-info/RECORD
