Metadata-Version: 2.1
Name: python-comwechatrobot-http
Version: 1.0.1
Summary: http api for comwechatrobot
Home-page: 
Author: honus
Author-email: honusmr@gmail.com
Keywords: wechatrobot
Classifier: Development Status :: 4 - Beta
Classifier: Intended Audience :: Developers
Classifier: Topic :: Software Development :: User Interfaces
Classifier: License :: OSI Approved :: MIT License
Classifier: Programming Language :: Python :: 3.7
Classifier: Operating System :: OS Independent
Requires-Python: >=3.7
Requires-Dist: requests
Requires-Dist: pydantic
Requires-Dist: protobuf (==3.20.1)
